vendor/__init__.py
vendor/__pycache__/__init__.cpython-39.pyc
sphinxcontrib_comments-0.0.1.dev0.dist-info/LICENSE
sphinxcontrib_comments-0.0.1.dev0.dist-info/METADATA
sphinxcontrib_comments-0.0.1.dev0.dist-info/WHEEL
sphinxcontrib_comments-0.0.1.dev0.dist-info/top_level.txt
sphinxcontrib_comments-0.0.1.dev0.dist-info/RECORD
